keybind/__init__.py
keybind/binder.py
keybind/cli.py
keybind-0.3.0.dist-info/AUTHORS
keybind-0.3.0.dist-info/LICENSE
keybind-0.3.0.dist-info/METADATA
keybind-0.3.0.dist-info/WHEEL
keybind-0.3.0.dist-info/entry_points.txt
keybind-0.3.0.dist-info/top_level.txt
keybind-0.3.0.dist-info/RECORD
